pcombinator/__init__.py
pcombinator/combinators/__init__.py
pcombinator/combinators/combinator.py
pcombinator/combinators/combinator_or_leaf_type.py
pcombinator/combinators/jinja2_template.py
pcombinator/combinators/join_some_of.py
pcombinator/combinators/named_string.py
pcombinator/combinators/pick_one.py
pcombinator/combinators/tests/__init__.py
pcombinator/combinators/tests/test_combinator.py
pcombinator/combinators/tests/test_jinja2_template.py
pcombinator/combinators/tests/test_join_some_of.py
pcombinator/combinators/tests/test_named_string.py
pcombinator/combinators/tests/test_pick_one.py
pcombinator/examples/prompt_atoms.py
pcombinator/persistence/__init__.py
pcombinator/persistence/prompt_candidates_file.py
pcombinator/persistence/tests/__init__.py
pcombinator/util/classname.py
pcombinator-0.0.3.dist-info/LICENSE
pcombinator-0.0.3.dist-info/METADATA
pcombinator-0.0.3.dist-info/WHEEL
pcombinator-0.0.3.dist-info/RECORD
