Metadata-Version: 2.1
Name: pcombinator
Version: 0.0.3
Summary: A tool for composing variations of prompts
License: Apache 2.0
Author: Roman Baron
Author-email: 1299323+RomansWorks@users.noreply.github.com
Requires-Python: >=3.9,<4.0
Classifier: Development Status :: 3 - Alpha
Classifier: Intended Audience :: Developers
Classifier: License :: OSI Approved :: Apache Software License
Classifier: License :: Other/Proprietary License
Classifier: Operating System :: OS Independent
Classifier: Programming Language :: Python :: 3
Classifier: Programming Language :: Python :: 3.9
Classifier: Programming Language :: Python :: 3.10
Classifier: Programming Language :: Python :: 3.11
Classifier: Programming Language :: Python :: 3.12
Classifier: Topic :: Software Development :: Libraries :: Python Modules
Classifier: Topic :: Text Processing :: Filters
Classifier: Topic :: Text Processing :: Linguistic
Provides-Extra: templating
Requires-Dist: jinja2 (>=3.1.2,<4.0.0) ; extra == "templating"
Requires-Dist: versioned_collection (>=0.0.1,<0.0.2)
